
{"items":[{"name":"Analysis","href":"analysis/index.html","topicHref":"analysis/index.html","includedFrom":"~/../../src/dotnet/tools/lucene-cli/docs/analysis/toc.yml","items":[{"name":"kuromoji-build-dictionary","href":"analysis/kuromoji-build-dictionary.html","topicHref":"analysis/kuromoji-build-dictionary.html"},{"name":"stempel-compile-stems","href":"analysis/stempel-compile-stems.html","topicHref":"analysis/stempel-compile-stems.html"},{"name":"stempel-patch-stems","href":"analysis/stempel-patch-stems.html","topicHref":"analysis/stempel-patch-stems.html"}]},{"name":"Benchmark","href":"benchmark/index.html","topicHref":"benchmark/index.html","includedFrom":"~/../../src/dotnet/tools/lucene-cli/docs/benchmark/toc.yml","items":[{"name":"extract-reuters","href":"benchmark/extract-reuters.html","topicHref":"benchmark/extract-reuters.html"},{"name":"extract-wikipedia","href":"benchmark/extract-wikipedia.html","topicHref":"benchmark/extract-wikipedia.html"},{"name":"find-quality-queries","href":"benchmark/find-quality-queries.html","topicHref":"benchmark/find-quality-queries.html"},{"name":"run-trec-eval","href":"benchmark/run-trec-eval.html","topicHref":"benchmark/run-trec-eval.html"},{"name":"run","href":"benchmark/run.html","topicHref":"benchmark/run.html"},{"name":"sample","href":"benchmark/sample.html","topicHref":"benchmark/sample.html"}]},{"name":"Index","href":"index/index.html","topicHref":"index/index.html","includedFrom":"~/../../src/dotnet/tools/lucene-cli/docs/index/toc.yml","items":[{"name":"check","href":"index/check.html","topicHref":"index/check.html"},{"name":"copy-segments","href":"index/copy-segments.html","topicHref":"index/copy-segments.html"},{"name":"delete-segments","href":"index/delete-segments.html","topicHref":"index/delete-segments.html"},{"name":"extract-cfs","href":"index/extract-cfs.html","topicHref":"index/extract-cfs.html"},{"name":"fix","href":"index/fix.html","topicHref":"index/fix.html"},{"name":"list-cfs","href":"index/list-cfs.html","topicHref":"index/list-cfs.html"},{"name":"list-high-freq-terms","href":"index/list-high-freq-terms.html","topicHref":"index/list-high-freq-terms.html"},{"name":"list-segments","href":"index/list-segments.html","topicHref":"index/list-segments.html"},{"name":"list-taxonomy-stats","href":"index/list-taxonomy-stats.html","topicHref":"index/list-taxonomy-stats.html"},{"name":"list-term-info","href":"index/list-term-info.html","topicHref":"index/list-term-info.html"},{"name":"merge","href":"index/merge.html","topicHref":"index/merge.html"},{"name":"split","href":"index/split.html","topicHref":"index/split.html"},{"name":"upgrade","href":"index/upgrade.html","topicHref":"index/upgrade.html"}]},{"name":"Lock","href":"lock/index.html","topicHref":"lock/index.html","includedFrom":"~/../../src/dotnet/tools/lucene-cli/docs/lock/toc.yml","items":[{"name":"stress-test","href":"lock/stress-test.html","topicHref":"lock/stress-test.html"},{"name":"verify-server","href":"lock/verify-server.html","topicHref":"lock/verify-server.html"}]},{"name":"Demo","href":"demo/index.html","topicHref":"demo/index.html","includedFrom":"~/../../src/dotnet/tools/lucene-cli/docs/demo/toc.yml","items":[{"name":"associations-facets","href":"demo/associations-facets.html","topicHref":"demo/associations-facets.html"},{"name":"distance-facets","href":"demo/distance-facets.html","topicHref":"demo/distance-facets.html"},{"name":"expression-aggregation-facets","href":"demo/expression-aggregation-facets.html","topicHref":"demo/expression-aggregation-facets.html"},{"name":"index-files","href":"demo/index-files.html","topicHref":"demo/index-files.html"},{"name":"multi-category-lists-facets","href":"demo/multi-category-lists-facets.html","topicHref":"demo/multi-category-lists-facets.html"},{"name":"range-facets","href":"demo/range-facets.html","topicHref":"demo/range-facets.html"},{"name":"search-files","href":"demo/search-files.html","topicHref":"demo/search-files.html"},{"name":"simple-facets","href":"demo/simple-facets.html","topicHref":"demo/simple-facets.html"},{"name":"simple-sorted-set-facets","href":"demo/simple-sorted-set-facets.html","topicHref":"demo/simple-sorted-set-facets.html"}]}]}
